{"DocumentId":"JD_template","ContentType":"application/pdf","Length":414,"Pages":[{"PageIndex":0,"Size":[0.0,0.0,612.0,792.0],"Sections":[{"IndexInText":0,"Language":"eng","Length":74,"Rotation":"None","SkewAngle":0.0,"Type":"Paragraph","WordGroups":[{"IndexInText":0,"Length":74,"Type":"Other","Words":[{"Box":[38.884,72.025,23.268,10.908],"Polygon":[72.025,38.884,95.293,38.884,95.293,49.792,72.025,49.792],"IndexInText":0,"OcrConfidence":1.0,"Text":"RPA","VisualLineNumber":0},{"Box":[38.884,98.233,34.104,10.908],"Polygon":[98.233,38.884,132.337,38.884,132.337,49.792,98.233,49.792],"IndexInText":4,"OcrConfidence":1.0,"Text":"Project","VisualLineNumber":0},{"Box":[38.884,135.385,46.776,10.908],"Polygon":[135.385,38.884,182.161,38.884,182.161,49.792,135.385,49.792],"IndexInText":12,"OcrConfidence":1.0,"Text":"Company","VisualLineNumber":0},{"Box":[52.714,72.025,51.144,10.908],"Polygon":[72.025,52.714,123.169,52.714,123.169,63.622,72.025,63.622],"IndexInText":20,"OcrConfidence":1.0,"Text":"Bucharest,","VisualLineNumber":1},{"Box":[52.714,126.169,43.296,10.908],"Polygon":[126.169,52.714,169.465,52.714,169.465,63.622,126.169,63.622],"IndexInText":31,"OcrConfidence":1.0,"Text":"Romania","VisualLineNumber":1},{"Box":[66.514,72.025,20.592,10.908],"Polygon":[72.025,66.514,92.617,66.514,92.617,77.422,72.025,77.422],"IndexInText":39,"OcrConfidence":1.0,"Text":"CUI","VisualLineNumber":2},{"Box":[66.514,95.617,40.608,10.908],"Polygon":[95.617,66.514,136.225,66.514,136.225,77.422,95.617,77.422],"IndexInText":43,"OcrConfidence":1.0,"Text":"J256983","VisualLineNumber":2},{"Box":[80.304,72.025,126.036,10.908],"Polygon":[72.025,80.304,198.061,80.304,198.061,91.212,72.025,91.212],"IndexInText":51,"OcrConfidence":1.0,"Text":"rpa_project@outlook.com","VisualLineNumber":3}]}]},{"IndexInText":76,"Language":"fra","Length":15,"Rotation":"None","SkewAngle":0.0,"Type":"Paragraph","WordGroups":[{"IndexInText":76,"Length":15,"Type":"Heading","Words":[{"Box":[124.906,251.28,23.388,10.716],"Polygon":[251.28,124.906,274.668,124.906,274.668,135.622,251.28,135.622],"IndexInText":76,"OcrConfidence":1.0,"Text":"JOB","VisualLineNumber":4},{"Box":[124.906,277.668,83.04,10.716],"Polygon":[277.668,124.906,360.708,124.906,360.708,135.622,277.668,135.622],"IndexInText":80,"OcrConfidence":1.0,"Text":"DESCRIPTION","VisualLineNumber":4}]}]},{"IndexInText":93,"Language":"eng","Length":7,"Rotation":"None","SkewAngle":0.0,"Type":"Paragraph","WordGroups":[{"IndexInText":93,"Length":7,"Type":"Heading","Words":[{"Box":[186.326,72.025,62.64,10.716],"Polygon":[72.025,186.326,134.665,186.326,134.665,197.042,72.025,197.042],"IndexInText":93,"OcrConfidence":1.0,"Text":"COMPANY","VisualLineNumber":5}]}]},{"IndexInText":102,"Language":"eng","Length":48,"Rotation":"None","SkewAngle":0.0,"Type":"Paragraph","WordGroups":[{"IndexInText":102,"Length":48,"Type":"Other","Words":[{"Box":[217.126,108.02,33.372,10.716],"Polygon":[108.02,217.126,141.392,217.126,141.392,227.842,108.02,227.842],"IndexInText":102,"OcrConfidence":1.0,"Text":"Name:","VisualLineNumber":6},{"Box":[216.934,144.45,45.304,10.908],"Polygon":[144.45,216.934,189.754,216.934,189.754,227.842,144.45,227.842],"IndexInText":108,"OcrConfidence":1.0,"Text":"Template","VisualLineNumber":6},{"Box":[216.934,192.814,46.572,10.908],"Polygon":[192.814,216.934,239.386,216.934,239.386,227.842,192.814,227.842],"IndexInText":117,"OcrConfidence":1.0,"Text":"Company","VisualLineNumber":6},{"Box":[247.726,108.02,34.226,10.716],"Polygon":[108.02,247.726,142.246,247.726,142.246,258.442,108.02,258.442],"IndexInText":125,"OcrConfidence":1.0,"Text":"Email:","VisualLineNumber":7},{"Box":[247.534,145.25,102.424,10.908],"Polygon":[145.25,247.534,247.674,247.534,247.674,258.442,145.25,258.442],"IndexInText":132,"OcrConfidence":1.0,"Text":"email@template.com","VisualLineNumber":7}]}]},{"IndexInText":152,"Language":"eng","Length":48,"Rotation":"None","SkewAngle":0.0,"Type":"Paragraph","WordGroups":[{"IndexInText":152,"Length":48,"Type":"Other","Words":[{"Box":[278.546,108.02,48.144,10.716],"Polygon":[108.02,278.546,156.164,278.546,156.164,289.262,108.02,289.262],"IndexInText":152,"OcrConfidence":1.0,"Text":"Location:","VisualLineNumber":8},{"Box":[278.354,159.25,47.9,10.908],"Polygon":[159.25,278.354,207.15,278.354,207.15,289.262,159.25,289.262],"IndexInText":162,"OcrConfidence":1.0,"Text":"Bucharest","VisualLineNumber":8},{"Box":[309.146,108.02,25.188,10.716],"Polygon":[108.02,309.146,133.208,309.146,133.208,319.862,108.02,319.862],"IndexInText":172,"OcrConfidence":1.0,"Text":"CUI:","VisualLineNumber":9},{"Box":[308.954,136.25,40.596,10.908],"Polygon":[136.25,308.954,176.846,308.954,176.846,319.862,136.25,319.862],"IndexInText":177,"OcrConfidence":1.0,"Text":"J001188","VisualLineNumber":9},{"Box":[339.946,72.025,23.388,10.716],"Polygon":[72.025,339.946,95.413,339.946,95.413,350.662,72.025,350.662],"IndexInText":185,"OcrConfidence":1.0,"Text":"JOB","VisualLineNumber":10},{"Box":[339.946,98.413,83.04,10.716],"Polygon":[98.413,339.946,181.453,339.946,181.453,350.662,98.413,350.662],"IndexInText":189,"OcrConfidence":1.0,"Text":"DESCRIPTION","VisualLineNumber":10}]}]},{"IndexInText":202,"Language":"fra","Length":44,"Rotation":"None","SkewAngle":0.0,"Type":"Paragraph","WordGroups":[{"IndexInText":202,"Length":44,"Type":"Other","Words":[{"Box":[370.576,108.02,45.804,10.716],"Polygon":[108.02,370.576,153.824,370.576,153.824,381.292,108.02,381.292],"IndexInText":202,"OcrConfidence":1.0,"Text":"JOB_ID:","VisualLineNumber":11},{"Box":[370.384,156.85,75.03,10.908],"Polygon":[156.85,370.384,231.88,370.384,231.88,381.292,156.85,381.292],"IndexInText":210,"OcrConfidence":1.0,"Text":"templatejob123","VisualLineNumber":11},{"Box":[401.376,108.02,38.736,10.716],"Polygon":[108.02,401.376,146.756,401.376,146.756,412.092,108.02,412.092],"IndexInText":225,"OcrConfidence":1.0,"Text":"Details:","VisualLineNumber":12},{"Box":[401.184,149.85,45.264,10.908],"Polygon":[149.85,401.184,195.114,401.184,195.114,412.092,149.85,412.092],"IndexInText":234,"OcrConfidence":1.0,"Text":"Template","VisualLineNumber":12},{"Box":[401.184,198.174,16.596,10.908],"Polygon":[198.174,401.184,214.77,401.184,214.77,412.092,198.174,412.092],"IndexInText":243,"OcrConfidence":1.0,"Text":"Job","VisualLineNumber":12}]}]},{"IndexInText":248,"Language":"eng","Length":63,"Rotation":"None","SkewAngle":0.0,"Type":"Paragraph","WordGroups":[{"IndexInText":248,"Length":63,"Type":"Other","Words":[{"Box":[431.976,108.02,48.744,10.716],"Polygon":[108.02,431.976,156.764,431.976,156.764,442.692,108.02,442.692],"IndexInText":248,"OcrConfidence":1.0,"Text":"Deadline:","VisualLineNumber":13},{"Box":[431.784,159.85,12.0,10.908],"Polygon":[159.85,431.784,171.85,431.784,171.85,442.692,159.85,442.692],"IndexInText":258,"OcrConfidence":1.0,"Text":"29","VisualLineNumber":13},{"Box":[431.784,174.85,49.344,10.908],"Polygon":[174.85,431.784,224.194,431.784,224.194,442.692,174.85,442.692],"IndexInText":261,"OcrConfidence":1.0,"Text":"December","VisualLineNumber":13},{"Box":[431.784,227.27,24.0,10.908],"Polygon":[227.27,431.784,251.27,431.784,251.27,442.692,227.27,442.692],"IndexInText":270,"OcrConfidence":1.0,"Text":"2021","VisualLineNumber":13},{"Box":[462.806,72.025,23.388,10.716],"Polygon":[72.025,462.806,95.413,462.806,95.413,473.522,72.025,473.522],"IndexInText":275,"OcrConfidence":1.0,"Text":"JOB","VisualLineNumber":14},{"Box":[462.806,98.413,98.448,10.716],"Polygon":[98.413,462.806,196.861,462.806,196.861,473.522,98.413,473.522],"IndexInText":279,"OcrConfidence":1.0,"Text":"REQUIREMENTS","VisualLineNumber":14},{"Box":[493.396,108.02,60.132,10.716],"Polygon":[108.02,493.396,168.152,493.396,168.152,504.112,108.02,504.112],"IndexInText":292,"OcrConfidence":1.0,"Text":"Experience:","VisualLineNumber":15},{"Box":[493.204,171.25,6.0,10.908],"Polygon":[171.25,493.204,177.25,493.204,177.25,504.112,171.25,504.112],"IndexInText":304,"OcrConfidence":1.0,"Text":"3","VisualLineNumber":15},{"Box":[493.204,180.25,25.248,10.908],"Polygon":[180.25,493.204,205.498,493.204,205.498,504.112,180.25,504.112],"IndexInText":306,"OcrConfidence":1.0,"Text":"years","VisualLineNumber":15}]}]},{"IndexInText":313,"Language":"eng","Length":68,"Rotation":"None","SkewAngle":0.0,"Type":"Paragraph","WordGroups":[{"IndexInText":313,"Length":68,"Type":"Other","Words":[{"Box":[524.206,108.02,31.344,10.716],"Polygon":[108.02,524.206,139.364,524.206,139.364,534.922,108.02,534.922],"IndexInText":313,"OcrConfidence":1.0,"Text":"Skills:","VisualLineNumber":16},{"Box":[524.014,142.45,29.8,10.908],"Polygon":[142.45,524.014,172.25,524.014,172.25,534.922,142.45,534.922],"IndexInText":321,"OcrConfidence":1.0,"Text":"skill1,","VisualLineNumber":16},{"Box":[524.014,175.25,29.568,10.908],"Polygon":[175.25,524.014,204.818,524.014,204.818,534.922,175.25,534.922],"IndexInText":329,"OcrConfidence":1.0,"Text":"skill2,","VisualLineNumber":16},{"Box":[524.014,207.818,29.862,10.908],"Polygon":[207.818,524.014,237.68,524.014,237.68,534.922,207.818,534.922],"IndexInText":337,"OcrConfidence":1.0,"Text":"skill3,","VisualLineNumber":16},{"Box":[524.014,240.68,26.568,10.908],"Polygon":[240.68,524.014,267.248,524.014,267.248,534.922,240.68,534.922],"IndexInText":345,"OcrConfidence":1.0,"Text":"skill4","VisualLineNumber":16},{"Box":[554.796,108.02,55.356,10.716],"Polygon":[108.02,554.796,163.376,554.796,163.376,565.512,108.02,565.512],"IndexInText":352,"OcrConfidence":1.0,"Text":"Education:","VisualLineNumber":17},{"Box":[554.604,166.45,41.256,10.908],"Polygon":[166.45,554.604,207.706,554.604,207.706,565.512,166.45,565.512],"IndexInText":363,"OcrConfidence":1.0,"Text":"template","VisualLineNumber":17},{"Box":[554.604,210.766,46.74,10.908],"Polygon":[210.766,554.604,257.506,554.604,257.506,565.512,210.766,565.512],"IndexInText":372,"OcrConfidence":1.0,"Text":"education","VisualLineNumber":17}]}]},{"IndexInText":383,"Language":"eng","Length":31,"Rotation":"None","SkewAngle":0.0,"Type":"Paragraph","WordGroups":[{"IndexInText":383,"Length":31,"Type":"Other","Words":[{"Box":[585.626,108.02,43.308,10.716],"Polygon":[108.02,585.626,151.328,585.626,151.328,596.342,108.02,596.342],"IndexInText":383,"OcrConfidence":1.0,"Text":"Optional","VisualLineNumber":18},{"Box":[585.626,154.376,29.34,10.716],"Polygon":[154.376,585.626,183.716,585.626,183.716,596.342,154.376,596.342],"IndexInText":392,"OcrConfidence":1.0,"Text":"skills:","VisualLineNumber":18},{"Box":[585.434,186.85,29.748,10.908],"Polygon":[186.85,585.434,216.598,585.434,216.598,596.342,186.85,596.342],"IndexInText":400,"OcrConfidence":1.0,"Text":"skill1,","VisualLineNumber":18},{"Box":[585.434,219.598,26.568,10.908],"Polygon":[219.598,585.434,246.166,585.434,246.166,596.342,219.598,596.342],"IndexInText":408,"OcrConfidence":1.0,"Text":"skill2","VisualLineNumber":18}]}]}],"ProcessingSource":"Pdf","IndexInText":0,"TextLength":414,"SkewAngle":0.0}]}